LICENSE
README.md
setup.py
yatomat/__init__.py
yatomat/benchmark.py
yatomat/chromosome.py
yatomat/core.py
yatomat/output.py
yatomat/repeats.py
yatomat/structures.py
yatomat/visualizer.py
yatomat/yatomat.py
yatomat.egg-info/PKG-INFO
yatomat.egg-info/SOURCES.txt
yatomat.egg-info/dependency_links.txt
yatomat.egg-info/entry_points.txt
yatomat.egg-info/requires.txt
yatomat.egg-info/top_level.txt
yatomat/regions/__init__.py
yatomat/regions/boundaries.py
yatomat/regions/centromeres.py
yatomat/regions/chromosome_regions.py
yatomat/regions/common.py
yatomat/regions/pericentromeres.py
yatomat/regions/telomers.py
yatomat/tests/__init__.py
yatomat/tests/test_boundaries.py
yatomat/tests/test_centromeres.py
yatomat/tests/test_chromosome_regions.py
yatomat/tests/test_common.py
yatomat/tests/test_core.py
yatomat/tests/test_pericentromeres.py
yatomat/tests/test_telomeres.py