Metadata-Version: 2.1
Name: yatomat
Version: 0.1.2
Summary: Yet Another Tool for Making Artificial Genomes
Home-page: https://github.com/aglabx/yatomat
Author: Marina Popova, Aleksey Komissarov
Author-email: ad3002@example.com
Project-URL: Bug Reports, https://github.com/aglabx/yatomat/issues
Project-URL: Source, https://github.com/aglabx/yatomat
Classifier: Programming Language :: Python :: 3
Classifier: License :: OSI Approved :: MIT License
Classifier: Operating System :: OS Independent
Classifier: Development Status :: 3 - Alpha
Classifier: Intended Audience :: Science/Research
Classifier: Topic :: Scientific/Engineering :: Bio-Informatics
Requires-Python: >=3.6
License-File: LICENSE
Requires-Dist: pandas
Requires-Dist: numpy
Requires-Dist: plotly
Requires-Dist: matplotlib
Requires-Dist: scipy
